{"application": "software-mentions", "version": "0.8.0", "date": "2024-03-21T10:07+0000", "md5": "70B4A13862331F1C537D72FC38B943AC", "mentions": [{"type": "software", "software-type": "environment", "wikidataId": "Q1204300", "wikipediaExternalRef": 1809002, "lang": "en", "confidence": 0.7626, "software-name": {"rawForm": "Stata", "normalizedForm": "Stata", "wikidataId": "Q1204300", "wikipediaExternalRef": 1809002, "lang": "en", "confidence": 0.7626, "offsetStart": 48, "offsetEnd": 53}, "version": {"rawForm": "16", "normalizedForm": "16", "offsetStart": 54, "offsetEnd": 56}, "context": "The statistical analyses were carried out using Stata 16. ", "mentionContextAttributes": {"used": {"value": true, "score": 0.9999977350234985}, "created": {"value": false, "score": 1.9073486328125e-06}, "shared": {"value": false, "score": 2.384185791015625e-07}}, "documentContextAttributes": {"used": {"value": true, "score": 0.9999977350234985}, "created": {"value": false, "score": 1.9073486328125e-06}, "shared": {"value": false, "score": 2.384185791015625e-07}}}], "references": [], "runtime": 10745, "id": "dffb08bc56a1d402af1df97fcfd23e14d37c1440", "metadata": {"id": "dffb08bc56a1d402af1df97fcfd23e14d37c1440"}, "original_file_path": "../../datalake/Samuel/SV22/SV22_xml/hal-03716864.grobid.tei.xml", "file_name": "hal-03716864.grobid.tei.xml"}