{"application": "software-mentions", "version": "0.8.0", "date": "2024-10-07T12:45+0000", "md5": "8799B07C51C025B91AFDAFDEF1A2CFE7", "mentions": [{"type": "software", "software-type": "software", "software-name": {"rawForm": "TopSum", "normalizedForm": "TopSum", "offsetStart": 0, "offsetEnd": 6}, "context": "TopSum can suffer from a similar shortcoming: if there is a duplicate line close to the ideal topic distribution, adding that line again will let the incremental summary under construction stay close to the ideal topic distribution.", "mentionContextAttributes": {"used": {"value": false, "score": 6.783008575439453e-05}, "created": {"value": false, "score": 3.0517578125e-05}, "shared": {"value": false, "score": 2.384185791015625e-07}}, "documentContextAttributes": {"used": {"value": true, "score": 0.9975927472114563}, "created": {"value": true, "score": 0.9885209798812866}, "shared": {"value": false, "score": 3.5762786865234375e-07}}}, {"type": "software", "software-type": "software", "software-name": {"rawForm": "TextRank", "normalizedForm": "TextRank", "offsetStart": 0, "offsetEnd": 8}, "context": "TextRank, and a topic distribution based method) to perform lyrics summarization, and show that adding contextual information helps such models to produce better summaries. ", "mentionContextAttributes": {"used": {"value": false, "score": 0.0007009506225585938}, "created": {"value": false, "score": 0.0001456737518310547}, "shared": {"value": false, "score": 2.384185791015625e-07}}, "documentContextAttributes": {"used": {"value": true, "score": 0.9770232439041138}, "created": {"value": true, "score": 0.9885209798812866}, "shared": {"value": false, "score": 4.76837158203125e-07}}, "references": [{"label": "(Mihalcea and Tarau, 2004)", "normalizedForm": "Mihalcea and Tarau, 2004", "refKey": 27}]}, {"type": "software", "software-type": "software", "software-name": {"rawForm": "TextRank", "normalizedForm": "TextRank", "offsetStart": 0, "offsetEnd": 8}, "context": "TextRank provides a score for each line, TopSum provides a distance between the topic distributions of an incremental summary and the original text, and f it provides the fitness of each line. ", "mentionContextAttributes": {"used": {"value": false, "score": 0.00018912553787231445}, "created": {"value": false, "score": 2.0623207092285156e-05}, "shared": {"value": false, "score": 3.5762786865234375e-07}}, "documentContextAttributes": {"used": {"value": true, "score": 0.9770232439041138}, "created": {"value": true, "score": 0.9885209798812866}, "shared": {"value": false, "score": 4.76837158203125e-07}}, "references": [{"label": "(Mihalcea and Tarau, 2004)", "normalizedForm": "Mihalcea and Tarau, 2004", "refKey": 27}]}, {"type": "software", "software-type": "software", "software-name": {"rawForm": "TextRank", "normalizedForm": "TextRank", "offsetStart": 10, "offsetEnd": 18}, "context": "While for TextRank we rely on the off-the-shelf implementation of (Barrios et al., 2016), in the following we describe the other two methods.", "mentionContextAttributes": {"used": {"value": false, "score": 0.00493168830871582}, "created": {"value": false, "score": 0.3489276170730591}, "shared": {"value": false, "score": 2.384185791015625e-07}}, "documentContextAttributes": {"used": {"value": true, "score": 0.9770232439041138}, "created": {"value": true, "score": 0.9885209798812866}, "shared": {"value": false, "score": 4.76837158203125e-07}}, "references": [{"label": "(Mihalcea and Tarau, 2004)", "normalizedForm": "Mihalcea and Tarau, 2004", "refKey": 27}]}, {"type": "software", "software-type": "software", "software-name": {"rawForm": "TextRank", "normalizedForm": "TextRank", "offsetStart": 11, "offsetEnd": 19}, "context": "We use the TextRank implementation5 of (Barrios et al., 2016) without removing stop words (lyrics lines in input can be quite short, therefore we avoid losing all content of the line if removing stop words). ", "mentionContextAttributes": {"used": {"value": true, "score": 0.9770232439041138}, "created": {"value": false, "score": 1.2874603271484375e-05}, "shared": {"value": false, "score": 4.76837158203125e-07}}, "documentContextAttributes": {"used": {"value": true, "score": 0.9770232439041138}, "created": {"value": true, "score": 0.9885209798812866}, "shared": {"value": false, "score": 4.76837158203125e-07}}, "references": [{"label": "(Mihalcea and Tarau, 2004)", "normalizedForm": "Mihalcea and Tarau, 2004", "refKey": 27}]}, {"type": "software", "software-type": "software", "software-name": {"rawForm": "Thumbnail", "normalizedForm": "Thumbnail", "offsetStart": 11, "offsetEnd": 20}, "context": "The Lyrics Thumbnail is computed using String-based distance between text segments to facilitate clustering.", "mentionContextAttributes": {"used": {"value": true, "score": 0.9986053109169006}, "created": {"value": false, "score": 4.649162292480469e-06}, "shared": {"value": false, "score": 1.1920928955078125e-07}}, "documentContextAttributes": {"used": {"value": true, "score": 0.9994286894798279}, "created": {"value": true, "score": 0.9998712539672852}, "shared": {"value": false, "score": 4.76837158203125e-07}}}, {"type": "software", "software-type": "software", "software-name": {"rawForm": "Thumbnail", "normalizedForm": "Thumbnail", "offsetStart": 16, "offsetEnd": 25}, "context": "A Lyrics Double Thumbnail consists of two segments: one from the fittest segment cluster (usually the chorus), and one from the second fittest segment cluster (usually the bridge).1", "mentionContextAttributes": {"used": {"value": false, "score": 0.0008115172386169434}, "created": {"value": false, "score": 0.00013780593872070312}, "shared": {"value": false, "score": 2.384185791015625e-07}}, "documentContextAttributes": {"used": {"value": true, "score": 0.9994286894798279}, "created": {"value": true, "score": 0.9998712539672852}, "shared": {"value": false, "score": 4.76837158203125e-07}}}, {"type": "software", "software-type": "software", "software-name": {"rawForm": "Thumbnail", "normalizedForm": "Thumbnail", "offsetStart": 17, "offsetEnd": 26}, "context": "While the Lyrics Thumbnail is generated from the full segment structure of the lyrics including its duplicate lines, all other models are fed with unique text lines as input (i.e.", "mentionContextAttributes": {"used": {"value": true, "score": 0.7759368419647217}, "created": {"value": false, "score": 2.09808349609375e-05}, "shared": {"value": false, "score": 3.5762786865234375e-07}}, "documentContextAttributes": {"used": {"value": true, "score": 0.9994286894798279}, "created": {"value": true, "score": 0.9998712539672852}, "shared": {"value": false, "score": 4.76837158203125e-07}}}, {"type": "software", "software-type": "software", "software-name": {"rawForm": "TopSum", "normalizedForm": "TopSum", "offsetStart": 41, "offsetEnd": 47}, "context": "TextRank provides a score for each line, TopSum provides a distance between the topic distributions of an incremental summary and the original text, and f it provides the fitness of each line. ", "mentionContextAttributes": {"used": {"value": false, "score": 0.00018912553787231445}, "created": {"value": false, "score": 2.0623207092285156e-05}, "shared": {"value": false, "score": 3.5762786865234375e-07}}, "documentContextAttributes": {"used": {"value": true, "score": 0.9975927472114563}, "created": {"value": true, "score": 0.9885209798812866}, "shared": {"value": false, "score": 3.5762786865234375e-07}}}, {"type": "software", "software-type": "software", "software-name": {"rawForm": "TopSum", "normalizedForm": "TopSum", "offsetStart": 41, "offsetEnd": 47}, "context": "Here x \u2208 (S \\ sum(S)) and A \u2208 {TextRank, TopSum, fit}.", "mentionContextAttributes": {"used": {"value": true, "score": 0.9975927472114563}, "created": {"value": false, "score": 4.649162292480469e-05}, "shared": {"value": false, "score": 2.384185791015625e-07}}, "documentContextAttributes": {"used": {"value": true, "score": 0.9975927472114563}, "created": {"value": true, "score": 0.9885209798812866}, "shared": {"value": false, "score": 3.5762786865234375e-07}}}, {"type": "software", "software-type": "software", "software-name": {"rawForm": "TextRank", "normalizedForm": "TextRank", "offsetStart": 43, "offsetEnd": 51}, "context": "We also produce two summaries by combining TextRank + TopSum and TextRank + TopSum + Lyrics Thumbnail, to test if summaries can benefit from the complementary perspectives the three different summarization methods take.", "mentionContextAttributes": {"used": {"value": false, "score": 0.0025028586387634277}, "created": {"value": false, "score": 0.3732515573501587}, "shared": {"value": false, "score": 2.384185791015625e-07}}, "documentContextAttributes": {"used": {"value": true, "score": 0.9770232439041138}, "created": {"value": true, "score": 0.9885209798812866}, "shared": {"value": false, "score": 4.76837158203125e-07}}, "references": [{"label": "(Mihalcea and Tarau, 2004)", "normalizedForm": "Mihalcea and Tarau, 2004", "refKey": 27}]}, {"type": "software", "software-type": "software", "software-name": {"rawForm": "TextRank", "normalizedForm": "TextRank", "offsetStart": 49, "offsetEnd": 57}, "context": "Model Nomenclature For abbreviation, we call the TextRank model henceforth M r , the Top-Sum model M s , the fitness-based summarizer M f , model combinations M rs and M rsf , respectively.", "mentionContextAttributes": {"used": {"value": false, "score": 0.00447005033493042}, "created": {"value": false, "score": 3.707408905029297e-05}, "shared": {"value": false, "score": 2.384185791015625e-07}}, "documentContextAttributes": {"used": {"value": true, "score": 0.9770232439041138}, "created": {"value": true, "score": 0.9885209798812866}, "shared": {"value": false, "score": 4.76837158203125e-07}}, "references": [{"label": "(Mihalcea and Tarau, 2004)", "normalizedForm": "Mihalcea and Tarau, 2004", "refKey": 27}]}, {"type": "software", "software-type": "software", "software-name": {"rawForm": "Thumbnail", "normalizedForm": "Thumbnail", "offsetStart": 49, "offsetEnd": 58}, "context": "Analog to an audio thumbnail, we define a Lyrics Thumbnail as the most representative and repetitive part of the song text.", "mentionContextAttributes": {"used": {"value": false, "score": 0.006868302822113037}, "created": {"value": false, "score": 0.0002632737159729004}, "shared": {"value": false, "score": 4.76837158203125e-07}}, "documentContextAttributes": {"used": {"value": true, "score": 0.9994286894798279}, "created": {"value": true, "score": 0.9998712539672852}, "shared": {"value": false, "score": 4.76837158203125e-07}}}, {"type": "software", "software-type": "software", "software-name": {"rawForm": "TextRank", "normalizedForm": "TextRank", "offsetStart": 53, "offsetEnd": 61}, "context": "Three of the most popular graphbased summarizers are TextRank (Mihalcea and Tarau, 2004), LexRank (Erkan and Radev, 2004), and (Parveen et al., 2015).", "mentionContextAttributes": {"used": {"value": false, "score": 0.0002098679542541504}, "created": {"value": false, "score": 3.6597251892089844e-05}, "shared": {"value": false, "score": 2.384185791015625e-07}}, "documentContextAttributes": {"used": {"value": true, "score": 0.9770232439041138}, "created": {"value": true, "score": 0.9885209798812866}, "shared": {"value": false, "score": 4.76837158203125e-07}}, "references": [{"label": "(Mihalcea and Tarau, 2004)", "normalizedForm": "Mihalcea and Tarau, 2004", "refKey": 27, "offsetStart": 6214, "offsetEnd": 6240}]}, {"type": "software", "software-type": "software", "software-name": {"rawForm": "TopSum", "normalizedForm": "TopSum", "offsetStart": 56, "offsetEnd": 62}, "context": "8 We also produce two summaries by combining TextRank + TopSum and TextRank + TopSum + Lyrics Thumbnail, to test if summaries can benefit from the complementary perspectives the three different summarization methods take.", "mentionContextAttributes": {"used": {"value": false, "score": 0.0044577717781066895}, "created": {"value": false, "score": 0.017709791660308838}, "shared": {"value": false, "score": 2.384185791015625e-07}}, "documentContextAttributes": {"used": {"value": true, "score": 0.9975927472114563}, "created": {"value": true, "score": 0.9885209798812866}, "shared": {"value": false, "score": 3.5762786865234375e-07}}}, {"type": "software", "software-type": "software", "software-name": {"rawForm": "TextRank + TopSum", "normalizedForm": "TextRank + TopSum", "offsetStart": 65, "offsetEnd": 82}, "context": "We also produce two summaries by combining TextRank + TopSum and TextRank + TopSum + Lyrics Thumbnail, to test if summaries can benefit from the complementary perspectives the three different summarization methods take.", "mentionContextAttributes": {"used": {"value": false, "score": 0.0025028586387634277}, "created": {"value": false, "score": 0.3732515573501587}, "shared": {"value": false, "score": 2.384185791015625e-07}}, "documentContextAttributes": {"used": {"value": false, "score": 0.0025028586387634277}, "created": {"value": false, "score": 0.3732515573501587}, "shared": {"value": false, "score": 2.384185791015625e-07}}}, {"type": "software", "software-type": "software", "software-name": {"rawForm": "TextRank", "normalizedForm": "TextRank", "offsetStart": 70, "offsetEnd": 78}, "context": "We have applied both generic unsupervised text summarization methods (TextRank and a topic-based method we called TopSum), and a method inspired by audio thumbnailing on 50k lyrics from the WASABI corpus.", "mentionContextAttributes": {"used": {"value": true, "score": 0.9393037557601929}, "created": {"value": true, "score": 0.9885209798812866}, "shared": {"value": false, "score": 2.384185791015625e-07}}, "documentContextAttributes": {"used": {"value": true, "score": 0.9770232439041138}, "created": {"value": true, "score": 0.9885209798812866}, "shared": {"value": false, "score": 4.76837158203125e-07}}, "references": [{"label": "(Mihalcea and Tarau, 2004)", "normalizedForm": "Mihalcea and Tarau, 2004", "refKey": 27}]}, {"type": "software", "software-type": "software", "software-name": {"rawForm": "Tex-tRank", "normalizedForm": "Tex-tRank", "offsetStart": 75, "offsetEnd": 84}, "context": "This is done to produce less redundant summaries, given that for instance, Tex-tRank scores each duplicate line the same, hence it may create summaries with all identical lines. ", "mentionContextAttributes": {"used": {"value": false, "score": 0.000999152660369873}, "created": {"value": false, "score": 3.814697265625e-05}, "shared": {"value": false, "score": 2.384185791015625e-07}}, "documentContextAttributes": {"used": {"value": false, "score": 0.000999152660369873}, "created": {"value": false, "score": 3.814697265625e-05}, "shared": {"value": false, "score": 2.384185791015625e-07}}}, {"type": "software", "software-type": "software", "software-name": {"rawForm": "Thumbnail", "normalizedForm": "Thumbnail", "offsetStart": 78, "offsetEnd": 87}, "context": "If the second fittest cluster has a fitness of 0, we generate a Lyrics Single Thumbnail solely from the fittest cluster (usually the chorus).", "mentionContextAttributes": {"used": {"value": true, "score": 0.8297617435455322}, "created": {"value": false, "score": 3.4570693969726562e-06}, "shared": {"value": false, "score": 1.1920928955078125e-07}}, "documentContextAttributes": {"used": {"value": true, "score": 0.9994286894798279}, "created": {"value": true, "score": 0.9998712539672852}, "shared": {"value": false, "score": 4.76837158203125e-07}}}, {"type": "software", "software-type": "software", "software-name": {"rawForm": "Thumbnail", "normalizedForm": "Thumbnail", "offsetStart": 84, "offsetEnd": 93}, "context": "Moreover, we introduce a method inspired by audio thumbnailing (which we dub Lyrics Thumbnail) which aims at creating a summary from the most representative parts of the original song text.", "mentionContextAttributes": {"used": {"value": false, "score": 8.058547973632812e-05}, "created": {"value": true, "score": 0.9998712539672852}, "shared": {"value": false, "score": 4.76837158203125e-07}}, "documentContextAttributes": {"used": {"value": true, "score": 0.9994286894798279}, "created": {"value": true, "score": 0.9998712539672852}, "shared": {"value": false, "score": 4.76837158203125e-07}}}, {"type": "software", "software-type": "software", "software-name": {"rawForm": "Thumbnail", "normalizedForm": "Thumbnail", "offsetStart": 90, "offsetEnd": 99}, "context": "We therefore estimate the median chorus length on our corpus by computing a Lyrics Single Thumbnail on each text, and we find the median chorus length to be 4 lines.", "mentionContextAttributes": {"used": {"value": true, "score": 0.9994286894798279}, "created": {"value": false, "score": 9.179115295410156e-06}, "shared": {"value": false, "score": 2.384185791015625e-07}}, "documentContextAttributes": {"used": {"value": true, "score": 0.9994286894798279}, "created": {"value": true, "score": 0.9998712539672852}, "shared": {"value": false, "score": 4.76837158203125e-07}}}, {"type": "software", "software-type": "software", "software-name": {"rawForm": "Thumbnail", "normalizedForm": "Thumbnail", "offsetStart": 92, "offsetEnd": 101}, "context": "We also produce two summaries by combining TextRank + TopSum and TextRank + TopSum + Lyrics Thumbnail, to test if summaries can benefit from the complementary perspectives the three different summarization methods take.", "mentionContextAttributes": {"used": {"value": false, "score": 0.0025028586387634277}, "created": {"value": false, "score": 0.3732515573501587}, "shared": {"value": false, "score": 2.384185791015625e-07}}, "documentContextAttributes": {"used": {"value": true, "score": 0.9994286894798279}, "created": {"value": true, "score": 0.9998712539672852}, "shared": {"value": false, "score": 4.76837158203125e-07}}}, {"type": "software", "software-type": "software", "software-name": {"rawForm": "TextRank", "normalizedForm": "TextRank", "offsetStart": 101, "offsetEnd": 109}, "context": "We create summaries using the three summarization methods described in Section 3, i.e. a graphbased (TextRank), a topic-based (TopSum), and fitness-based (Lyrics Thumbnail) method, plus two additional combined models (described below).", "mentionContextAttributes": {"used": {"value": false, "score": 0.12088727951049805}, "created": {"value": false, "score": 0.000867307186126709}, "shared": {"value": false, "score": 2.384185791015625e-07}}, "documentContextAttributes": {"used": {"value": true, "score": 0.9770232439041138}, "created": {"value": true, "score": 0.9885209798812866}, "shared": {"value": false, "score": 4.76837158203125e-07}}, "references": [{"label": "(Mihalcea and Tarau, 2004)", "normalizedForm": "Mihalcea and Tarau, 2004", "refKey": 27}]}, {"type": "software", "software-type": "software", "software-name": {"rawForm": "TextRank", "normalizedForm": "TextRank", "offsetStart": 109, "offsetEnd": 117}, "context": "To address this task, we apply the following methods from the literature: the popular graph-based summarizer TextRank; an adaptation of a topic-based method (TopSum). ", "mentionContextAttributes": {"used": {"value": false, "score": 0.015746116638183594}, "created": {"value": false, "score": 0.10514718294143677}, "shared": {"value": false, "score": 2.384185791015625e-07}}, "documentContextAttributes": {"used": {"value": true, "score": 0.9770232439041138}, "created": {"value": true, "score": 0.9885209798812866}, "shared": {"value": false, "score": 4.76837158203125e-07}}, "references": [{"label": "(Mihalcea and Tarau, 2004)", "normalizedForm": "Mihalcea and Tarau, 2004", "refKey": 27}]}, {"type": "software", "software-type": "software", "software-name": {"rawForm": "TopSum", "normalizedForm": "TopSum", "offsetStart": 114, "offsetEnd": 120}, "context": "We have applied both generic unsupervised text summarization methods (TextRank and a topic-based method we called TopSum), and a method inspired by audio thumbnailing on 50k lyrics from the WASABI corpus.", "mentionContextAttributes": {"used": {"value": true, "score": 0.9393037557601929}, "created": {"value": true, "score": 0.9885209798812866}, "shared": {"value": false, "score": 2.384185791015625e-07}}, "documentContextAttributes": {"used": {"value": true, "score": 0.9975927472114563}, "created": {"value": true, "score": 0.9885209798812866}, "shared": {"value": false, "score": 3.5762786865234375e-07}}}, {"type": "software", "software-type": "software", "software-name": {"rawForm": "TopSum", "normalizedForm": "TopSum", "offsetStart": 127, "offsetEnd": 133}, "context": "We create summaries using the three summarization methods described in Section 3, i.e. a graphbased (TextRank), a topic-based (TopSum), and fitness-based (Lyrics Thumbnail) method, plus two additional combined models (described below).", "mentionContextAttributes": {"used": {"value": false, "score": 0.12088727951049805}, "created": {"value": false, "score": 0.000867307186126709}, "shared": {"value": false, "score": 2.384185791015625e-07}}, "documentContextAttributes": {"used": {"value": true, "score": 0.9975927472114563}, "created": {"value": true, "score": 0.9885209798812866}, "shared": {"value": false, "score": 3.5762786865234375e-07}}}, {"type": "software", "software-type": "software", "software-name": {"rawForm": "TopSum", "normalizedForm": "TopSum", "offsetStart": 158, "offsetEnd": 164}, "context": "To address this task, we apply the following methods from the literature: the popular graph-based summarizer TextRank; an adaptation of a topic-based method (TopSum). ", "mentionContextAttributes": {"used": {"value": false, "score": 0.015746116638183594}, "created": {"value": false, "score": 0.10514718294143677}, "shared": {"value": false, "score": 2.384185791015625e-07}}, "documentContextAttributes": {"used": {"value": true, "score": 0.9975927472114563}, "created": {"value": true, "score": 0.9885209798812866}, "shared": {"value": false, "score": 3.5762786865234375e-07}}}, {"type": "software", "software-type": "software", "software-name": {"rawForm": "Thumbnail", "normalizedForm": "Thumbnail", "offsetStart": 162, "offsetEnd": 171}, "context": "We create summaries using the three summarization methods described in Section 3, i.e. a graphbased (TextRank), a topic-based (TopSum), and fitness-based (Lyrics Thumbnail) method, plus two additional combined models (described below).", "mentionContextAttributes": {"used": {"value": false, "score": 0.12088727951049805}, "created": {"value": false, "score": 0.000867307186126709}, "shared": {"value": false, "score": 2.384185791015625e-07}}, "documentContextAttributes": {"used": {"value": true, "score": 0.9994286894798279}, "created": {"value": true, "score": 0.9998712539672852}, "shared": {"value": false, "score": 4.76837158203125e-07}}}], "references": [{"refKey": 27, "tei": "<biblStruct xml:id=\"b27\">\n\t<analytic>\n\t\t<title level=\"a\" type=\"main\">Textrank: Bringing order into text</title>\n\t\t<author>\n\t\t\t<persName><forename type=\"first\">Rada</forename><surname>Mihalcea</surname></persName>\n\t\t</author>\n\t\t<author>\n\t\t\t<persName><forename type=\"first\">Paul</forename><surname>Tarau</surname></persName>\n\t\t</author>\n\t</analytic>\n\t<monogr>\n\t\t<title level=\"m\">Proceedings of the 2004 Conference on Empirical Methods in Natural Language Processing</title>\n\t\t<meeting>the 2004 Conference on Empirical Methods in Natural Language Processing</meeting>\n\t\t<imprint>\n\t\t\t<date>2004</date>\n\t\t</imprint>\n\t</monogr>\n</biblStruct>\n"}], "runtime": 18843, "id": "435769c06770e1f6b585b56188f61d43c34e3077", "metadata": {"id": "435769c06770e1f6b585b56188f61d43c34e3077"}, "original_file_path": "../../datalake/Samuel/SOFTware-Sync/downloads/xml/hal-02281138.grobid.tei.xml", "file_name": "hal-02281138.grobid.tei.xml"}